EasyDAG/__init__.py
EasyDAG/core.py
EasyDAG/dag_types.py
EasyDAG/interface.py
EasyDAG/node.py
EasyDAG/queue.py
easydag-0.2.0.dist-info/METADATA
easydag-0.2.0.dist-info/WHEEL
easydag-0.2.0.dist-info/licenses/LICENSE
easydag-0.2.0.dist-info/RECORD
