Metadata-Version: 2.3
Name: EasyDAG
Version: 0.2.0
Summary: A lightweight multiprocessing DAG execution engine with message queues and external control options.
Project-URL: Homepage, https://github.com/mechatronicist/EasyDAG
Project-URL: Repository, https://github.com/mechatronicist/EasyDAG
Project-URL: Issues, https://github.com/mechatronicist/EasyDAG/issues
Author: Mechatronicist
License: MIT License
Keywords: dag,multiprocessing,parallel,tasks,workflow
Requires-Python: >=3.9
